tinydb/__init__.py
tinydb/database.py
tinydb/middlewares.py
tinydb/mypy_plugin.py
tinydb/operations.py
tinydb/py.typed
tinydb/queries.py
tinydb/storages.py
tinydb/table.py
tinydb/utils.py
tinydb/version.py
tinydb-4.6.0.dist-info/LICENSE
tinydb-4.6.0.dist-info/WHEEL
tinydb-4.6.0.dist-info/METADATA
tinydb-4.6.0.dist-info/RECORD
