Metadata-Version: 2.1
Name: tinydb
Version: 4.6.0
Summary: TinyDB is a tiny, document oriented database optimized for your happiness :)
Home-page: https://github.com/msiemens/tinydb
License: MIT
Keywords: database,nosql
Author: Markus Siemens
Author-email: markus@m-siemens.de
Requires-Python: >=3.6,<4.0
Classifier: Development Status :: 5 - Production/Stable
Classifier: Intended Audience :: Developers
Classifier: Intended Audience :: System Administrators
Classifier: License :: OSI Approved :: MIT License
Classifier: Operating System :: OS Independent
Classifier: Programming Language :: Python :: 3
Classifier: Programming Language :: Python :: 3.10
Classifier: Programming Language :: Python :: 3.6
Classifier: Programming Language :: Python :: 3.7
Classifier: Programming Language :: Python :: 3.8
Classifier: Programming Language :: Python :: 3.9
Classifier: Programming Language :: Python :: Implementation :: CPython
Classifier: Programming Language :: Python :: Implementation :: PyPy
Classifier: Topic :: Database
Classifier: Topic :: Database :: Database Engines/Servers
Classifier: Topic :: Utilities
Classifier: Typing :: Typed
Requires-Dist: typing-extensions (>=3.10.0,<5.0.0); python_version <= "3.7"
Project-URL: Changelog, https://github.com/msiemens/tinydb/en/latest/changelog.html
Project-URL: Documentation, https://tinydb.readthedocs.org/
Project-URL: Issues, https://github.com/msiemens/tinydb/issues
